specbook/__init__.py
specbook/__main__.py
specbook/cli.py
specbook/core/__init__.py
specbook/core/finder.py
specbook/core/models.py
specbook/core/server.py
specbook/ui/__init__.py
specbook/ui/console.py
specbook/ui/web/__init__.py
specbook/ui/web/app.py
specbook/ui/web/static/specbook_leaf.png
specbook/ui/web/static/specbook_leaf_lavender.png
specbook/ui/web/static/specbook_leaf_white.png
specbook/ui/web/templates/index.html
specbook-0.0.1.dist-info/METADATA
specbook-0.0.1.dist-info/WHEEL
specbook-0.0.1.dist-info/entry_points.txt
specbook-0.0.1.dist-info/licenses/LICENSE
specbook-0.0.1.dist-info/RECORD
