Metadata-Version: 2.4
Name: specbook
Version: 0.0.1
Summary: CLI tool to collaborate on spec-driven development (SDD)
Author: Christopher Correa
License: BSD 3-Clause License
License-File: LICENSE
Requires-Python: >=3.11
Requires-Dist: jinja2>=3.1
Requires-Dist: psutil>=5.9
Requires-Dist: rich>=13
Requires-Dist: starlette>=0.40
Requires-Dist: typer>=0.9
Requires-Dist: uvicorn>=0.30
Provides-Extra: dev
Requires-Dist: pyright>=1.1; extra == 'dev'
Requires-Dist: pytest-cov>=4.1; extra == 'dev'
Requires-Dist: pytest>=7.4; extra == 'dev'
